drf_problems/__init__.py
drf_problems/apps.py
drf_problems/exceptions.py
drf_problems/mixins.py
drf_problems/permissions.py
drf_problems/serializers.py
drf_problems/tests.py
drf_problems/urls.py
drf_problems/utils.py
drf_problems/views.py
drf_problems/migrations/__init__.py
drf_problems-1.0.5.dist-info/LICENSE
drf_problems-1.0.5.dist-info/METADATA
drf_problems-1.0.5.dist-info/WHEEL
drf_problems-1.0.5.dist-info/top_level.txt
drf_problems-1.0.5.dist-info/RECORD
