Metadata-Version: 2.1
Name: drf-problems
Version: 1.0.5
Summary: Never liked DRF plain old errors? Forget that and accept RFC 7807 - Problem Details!
Home-page: https://github.com/shivanshs9/drf-problems/
Author: shivanshs9
Author-email: shivanshs9@gmail.com
License: MIT
License-File: LICENSE
Requires-Dist: Django (>=1.6)
Requires-Dist: djangorestframework (>=3.0.0)
